irescue/__init__.py
irescue/_genomes.py
irescue/_version.py
irescue/count.py
irescue/em.py
irescue/main.py
irescue/map.py
irescue/misc.py
irescue/network.py
IRescue-1.1.2.dist-info/LICENSE
IRescue-1.1.2.dist-info/METADATA
IRescue-1.1.2.dist-info/WHEEL
IRescue-1.1.2.dist-info/entry_points.txt
IRescue-1.1.2.dist-info/top_level.txt
IRescue-1.1.2.dist-info/RECORD
