Metadata-Version: 2.1
Name: IRescue
Version: 1.1.2
Summary: Interspersed Repeats singl-cell quantifier
Author-email: Benedetto Polimeni <polimeni@ingm.org>
License: MIT License
Project-URL: Source Code, https://github.com/bodegalab/irescue
Project-URL: Documentation, https://github.com/bodegalab/irescue#readme
Project-URL: Bug Tracker, https://github.com/bodegalab/irescue/issues
Keywords: bioinformatics,transposable-elements,scrna-seq,single-cell,single-cell-rna-seq
Classifier: Intended Audience :: Science/Research
Classifier: License :: OSI Approved :: MIT License
Classifier: Operating System :: OS Independent
Classifier: Programming Language :: Python :: 3.8
Classifier: Programming Language :: Python :: 3.9
Classifier: Programming Language :: Python :: 3.10
Classifier: Programming Language :: Python :: 3.11
Classifier: Programming Language :: Python :: 3.12
Classifier: Topic :: Scientific/Engineering :: Bio-Informatics
Requires-Python: >=3.8
License-File: LICENSE
Requires-Dist: numpy >=1.20.2
Requires-Dist: pysam >=0.16.0.1
Requires-Dist: requests >=2.27.1
Requires-Dist: networkx >=3.1
